[{"bucket":"pagerank-burst","key":"bigdata/edges/part-00024","timestamps":[{"key":"worker_start","value":"1713959399015"},{"key":"get_input","value":"1713959402663"},{"key":"calc_outlinks","value":"1713959402692"},{"key":"iter_0_start","value":"1713959402692"},{"key":"iter_0_broadcast_weights","value":"1713959409023"},{"key":"iter_0_calc_sums","value":"1713959411946"},{"key":"iter_0_reduce","value":"1713959417636"},{"key":"iter_0_calc_err","value":"1713959417636"},{"key":"iter_0_broadcast_err","value":"1713959421315"},{"key":"iter_0_end","value":"1713959421483"},{"key":"iter_1_start","value":"1713959421483"},{"key":"iter_1_broadcast_weights","value":"1713959427685"},{"key":"iter_1_calc_sums","value":"1713959429355"},{"key":"iter_1_reduce","value":"1713959434644"},{"key":"iter_1_calc_err","value":"1713959434644"},{"key":"iter_1_broadcast_err","value":"1713959438227"},{"key":"iter_1_end","value":"1713959438391"},{"key":"iter_2_start","value":"1713959438391"},{"key":"iter_2_broadcast_weights","value":"1713959444407"},{"key":"iter_2_calc_sums","value":"1713959445941"},{"key":"iter_2_reduce","value":"1713959451511"},{"key":"iter_2_calc_err","value":"1713959451511"},{"key":"iter_2_broadcast_err","value":"1713959455199"},{"key":"iter_2_end","value":"1713959455363"},{"key":"iter_3_start","value":"1713959455363"},{"key":"iter_3_broadcast_weights","value":"1713959461499"},{"key":"iter_3_calc_sums","value":"1713959463151"},{"key":"iter_3_reduce","value":"1713959468516"},{"key":"iter_3_calc_err","value":"1713959468516"},{"key":"iter_3_broadcast_err","value":"1713959472080"},{"key":"iter_3_end","value":"1713959472242"},{"key":"iter_4_start","value":"1713959472242"},{"key":"iter_4_broadcast_weights","value":"1713959478378"},{"key":"iter_4_calc_sums","value":"1713959479797"},{"key":"iter_4_reduce","value":"1713959485805"},{"key":"iter_4_calc_err","value":"1713959485805"},{"key":"iter_4_broadcast_err","value":"1713959489275"},{"key":"iter_4_end","value":"1713959489433"},{"key":"iter_5_start","value":"1713959489433"},{"key":"iter_5_broadcast_weights","value":"1713959495576"},{"key":"iter_5_calc_sums","value":"1713959497182"},{"key":"iter_5_reduce","value":"1713959502569"},{"key":"iter_5_calc_err","value":"1713959502569"},{"key":"iter_5_broadcast_err","value":"1713959506340"},{"key":"iter_5_end","value":"1713959506491"},{"key":"iter_6_start","value":"1713959506491"},{"key":"iter_6_broadcast_weights","value":"1713959512396"},{"key":"iter_6_calc_sums","value":"1713959513848"},{"key":"iter_6_reduce","value":"1713959519845"},{"key":"iter_6_calc_err","value":"1713959519845"},{"key":"iter_6_broadcast_err","value":"1713959523444"},{"key":"iter_6_end","value":"1713959523616"},{"key":"iter_7_start","value":"1713959523616"},{"key":"iter_7_broadcast_weights","value":"1713959529572"},{"key":"iter_7_calc_sums","value":"1713959530942"},{"key":"iter_7_reduce","value":"1713959536999"},{"key":"iter_7_calc_err","value":"1713959536999"},{"key":"iter_7_broadcast_err","value":"1713959540621"},{"key":"iter_7_end","value":"1713959540778"},{"key":"iter_8_start","value":"1713959540778"},{"key":"iter_8_broadcast_weights","value":"1713959546719"},{"key":"iter_8_calc_sums","value":"1713959548217"},{"key":"iter_8_reduce","value":"1713959554219"},{"key":"iter_8_calc_err","value":"1713959554219"},{"key":"iter_8_broadcast_err","value":"1713959557888"},{"key":"iter_8_end","value":"1713959558054"},{"key":"iter_9_start","value":"1713959558054"},{"key":"iter_9_broadcast_weights","value":"1713959564347"},{"key":"iter_9_calc_sums","value":"1713959565882"},{"key":"iter_9_reduce","value":"1713959571122"},{"key":"iter_9_calc_err","value":"1713959571122"},{"key":"iter_9_broadcast_err","value":"1713959574902"},{"key":"iter_9_end","value":"1713959575056"},{"key":"worker_end","value":"1713959575056"}]},{"bucket":"pagerank-burst","key":"bigdata/edges/part-00025","timestamps":[{"key":"worker_start","value":"1713959399015"},{"key":"get_input","value":"1713959402435"},{"key":"calc_outlinks","value":"1713959402490"},{"key":"iter_0_start","value":"1713959402490"},{"key":"iter_0_broadcast_weights","value":"1713959409151"},{"key":"iter_0_calc_sums","value":"1713959411901"},{"key":"iter_0_reduce","value":"1713959412918"},{"key":"iter_0_calc_err","value":"1713959412918"},{"key":"iter_0_broadcast_err","value":"1713959421315"},{"key":"iter_0_end","value":"1713959421481"},{"key":"iter_1_start","value":"1713959421481"},{"key":"iter_1_broadcast_weights","value":"1713959428059"},{"key":"iter_1_calc_sums","value":"1713959429806"},{"key":"iter_1_reduce","value":"1713959430579"},{"key":"iter_1_calc_err","value":"1713959430579"},{"key":"iter_1_broadcast_err","value":"1713959438227"},{"key":"iter_1_end","value":"1713959438386"},{"key":"iter_2_start","value":"1713959438386"},{"key":"iter_2_broadcast_weights","value":"1713959444892"},{"key":"iter_2_calc_sums","value":"1713959446641"},{"key":"iter_2_reduce","value":"1713959447472"},{"key":"iter_2_calc_err","value":"1713959447472"},{"key":"iter_2_broadcast_err","value":"1713959455199"},{"key":"iter_2_end","value":"1713959455363"},{"key":"iter_3_start","value":"1713959455363"},{"key":"iter_3_broadcast_weights","value":"1713959461950"},{"key":"iter_3_calc_sums","value":"1713959463580"},{"key":"iter_3_reduce","value":"1713959464352"},{"key":"iter_3_calc_err","value":"1713959464352"},{"key":"iter_3_broadcast_err","value":"1713959472080"},{"key":"iter_3_end","value":"1713959472242"},{"key":"iter_4_start","value":"1713959472242"},{"key":"iter_4_broadcast_weights","value":"1713959478944"},{"key":"iter_4_calc_sums","value":"1713959480652"},{"key":"iter_4_reduce","value":"1713959481439"},{"key":"iter_4_calc_err","value":"1713959481439"},{"key":"iter_4_broadcast_err","value":"1713959489276"},{"key":"iter_4_end","value":"1713959489434"},{"key":"iter_5_start","value":"1713959489434"},{"key":"iter_5_broadcast_weights","value":"1713959496065"},{"key":"iter_5_calc_sums","value":"1713959497790"},{"key":"iter_5_reduce","value":"1713959498645"},{"key":"iter_5_calc_err","value":"1713959498645"},{"key":"iter_5_broadcast_err","value":"1713959506340"},{"key":"iter_5_end","value":"1713959506498"},{"key":"iter_6_start","value":"1713959506498"},{"key":"iter_6_broadcast_weights","value":"1713959513031"},{"key":"iter_6_calc_sums","value":"1713959514695"},{"key":"iter_6_reduce","value":"1713959515511"},{"key":"iter_6_calc_err","value":"1713959515511"},{"key":"iter_6_broadcast_err","value":"1713959523444"},{"key":"iter_6_end","value":"1713959523611"},{"key":"iter_7_start","value":"1713959523611"},{"key":"iter_7_broadcast_weights","value":"1713959529479"},{"key":"iter_7_calc_sums","value":"1713959530966"},{"key":"iter_7_reduce","value":"1713959531736"},{"key":"iter_7_calc_err","value":"1713959531736"},{"key":"iter_7_broadcast_err","value":"1713959540621"},{"key":"iter_7_end","value":"1713959540789"},{"key":"iter_8_start","value":"1713959540789"},{"key":"iter_8_broadcast_weights","value":"1713959547378"},{"key":"iter_8_calc_sums","value":"1713959549171"},{"key":"iter_8_reduce","value":"1713959549956"},{"key":"iter_8_calc_err","value":"1713959549956"},{"key":"iter_8_broadcast_err","value":"1713959557888"},{"key":"iter_8_end","value":"1713959558059"},{"key":"iter_9_start","value":"1713959558059"},{"key":"iter_9_broadcast_weights","value":"1713959564262"},{"key":"iter_9_calc_sums","value":"1713959565981"},{"key":"iter_9_reduce","value":"1713959566838"},{"key":"iter_9_calc_err","value":"1713959566838"},{"key":"iter_9_broadcast_err","value":"1713959574902"},{"key":"iter_9_end","value":"1713959575066"},{"key":"worker_end","value":"1713959575066"}]},{"bucket":"pagerank-burst","key":"bigdata/edges/part-00026","timestamps":[{"key":"worker_start","value":"1713959399015"},{"key":"get_input","value":"1713959402624"},{"key":"calc_outlinks","value":"1713959402663"},{"key":"iter_0_start","value":"1713959402663"},{"key":"iter_0_broadcast_weights","value":"1713959408911"},{"key":"iter_0_calc_sums","value":"1713959411838"},{"key":"iter_0_reduce","value":"1713959414302"},{"key":"iter_0_calc_err","value":"1713959414303"},{"key":"iter_0_broadcast_err","value":"1713959421315"},{"key":"iter_0_end","value":"1713959421481"},{"key":"iter_1_start","value":"1713959421481"},{"key":"iter_1_broadcast_weights","value":"1713959427648"},{"key":"iter_1_calc_sums","value":"1713959429208"},{"key":"iter_1_reduce","value":"1713959431260"},{"key":"iter_1_calc_err","value":"1713959431260"},{"key":"iter_1_broadcast_err","value":"1713959438227"},{"key":"iter_1_end","value":"1713959438393"},{"key":"iter_2_start","value":"1713959438393"},{"key":"iter_2_broadcast_weights","value":"1713959444487"},{"key":"iter_2_calc_sums","value":"1713959446145"},{"key":"iter_2_reduce","value":"1713959448043"},{"key":"iter_2_calc_err","value":"1713959448043"},{"key":"iter_2_broadcast_err","value":"1713959455199"},{"key":"iter_2_end","value":"1713959455374"},{"key":"iter_3_start","value":"1713959455374"},{"key":"iter_3_broadcast_weights","value":"1713959461436"},{"key":"iter_3_calc_sums","value":"1713959462995"},{"key":"iter_3_reduce","value":"1713959465034"},{"key":"iter_3_calc_err","value":"1713959465034"},{"key":"iter_3_broadcast_err","value":"1713959472080"},{"key":"iter_3_end","value":"1713959472250"},{"key":"iter_4_start","value":"1713959472250"},{"key":"iter_4_broadcast_weights","value":"1713959478466"},{"key":"iter_4_calc_sums","value":"1713959480044"},{"key":"iter_4_reduce","value":"1713959482236"},{"key":"iter_4_calc_err","value":"1713959482236"},{"key":"iter_4_broadcast_err","value":"1713959489276"},{"key":"iter_4_end","value":"1713959489438"},{"key":"iter_5_start","value":"1713959489438"},{"key":"iter_5_broadcast_weights","value":"1713959495529"},{"key":"iter_5_calc_sums","value":"1713959497160"},{"key":"iter_5_reduce","value":"1713959499120"},{"key":"iter_5_calc_err","value":"1713959499120"},{"key":"iter_5_broadcast_err","value":"1713959506340"},{"key":"iter_5_end","value":"1713959506502"},{"key":"iter_6_start","value":"1713959506502"},{"key":"iter_6_broadcast_weights","value":"1713959512493"},{"key":"iter_6_calc_sums","value":"1713959513937"},{"key":"iter_6_reduce","value":"1713959516160"},{"key":"iter_6_calc_err","value":"1713959516160"},{"key":"iter_6_broadcast_err","value":"1713959523444"},{"key":"iter_6_end","value":"1713959523611"},{"key":"iter_7_start","value":"1713959523611"},{"key":"iter_7_broadcast_weights","value":"1713959530178"},{"key":"iter_7_calc_sums","value":"1713959531939"},{"key":"iter_7_reduce","value":"1713959533551"},{"key":"iter_7_calc_err","value":"1713959533551"},{"key":"iter_7_broadcast_err","value":"1713959540621"},{"key":"iter_7_end","value":"1713959540790"},{"key":"iter_8_start","value":"1713959540790"},{"key":"iter_8_broadcast_weights","value":"1713959546850"},{"key":"iter_8_calc_sums","value":"1713959548377"},{"key":"iter_8_reduce","value":"1713959550631"},{"key":"iter_8_calc_err","value":"1713959550631"},{"key":"iter_8_broadcast_err","value":"1713959557888"},{"key":"iter_8_end","value":"1713959558063"},{"key":"iter_9_start","value":"1713959558063"},{"key":"iter_9_broadcast_weights","value":"1713959564179"},{"key":"iter_9_calc_sums","value":"1713959565837"},{"key":"iter_9_reduce","value":"1713959568472"},{"key":"iter_9_calc_err","value":"1713959568473"},{"key":"iter_9_broadcast_err","value":"1713959574902"},{"key":"iter_9_end","value":"1713959575077"},{"key":"worker_end","value":"1713959575077"}]},{"bucket":"pagerank-burst","key":"bigdata/edges/part-00027","timestamps":[{"key":"worker_start","value":"1713959399015"},{"key":"get_input","value":"1713959402301"},{"key":"calc_outlinks","value":"1713959402352"},{"key":"iter_0_start","value":"1713959402352"},{"key":"iter_0_broadcast_weights","value":"1713959409678"},{"key":"iter_0_calc_sums","value":"1713959412150"},{"key":"iter_0_reduce","value":"1713959413007"},{"key":"iter_0_calc_err","value":"1713959413008"},{"key":"iter_0_broadcast_err","value":"1713959421315"},{"key":"iter_0_end","value":"1713959421482"},{"key":"iter_1_start","value":"1713959421482"},{"key":"iter_1_broadcast_weights","value":"1713959427611"},{"key":"iter_1_calc_sums","value":"1713959429146"},{"key":"iter_1_reduce","value":"1713959429960"},{"key":"iter_1_calc_err","value":"1713959429960"},{"key":"iter_1_broadcast_err","value":"1713959438227"},{"key":"iter_1_end","value":"1713959438387"},{"key":"iter_2_start","value":"1713959438387"},{"key":"iter_2_broadcast_weights","value":"1713959444259"},{"key":"iter_2_calc_sums","value":"1713959445855"},{"key":"iter_2_reduce","value":"1713959446722"},{"key":"iter_2_calc_err","value":"1713959446722"},{"key":"iter_2_broadcast_err","value":"1713959455199"},{"key":"iter_2_end","value":"1713959455373"},{"key":"iter_3_start","value":"1713959455373"},{"key":"iter_3_broadcast_weights","value":"1713959461356"},{"key":"iter_3_calc_sums","value":"1713959462923"},{"key":"iter_3_reduce","value":"1713959463719"},{"key":"iter_3_calc_err","value":"1713959463719"},{"key":"iter_3_broadcast_err","value":"1713959472080"},{"key":"iter_3_end","value":"1713959472254"},{"key":"iter_4_start","value":"1713959472254"},{"key":"iter_4_broadcast_weights","value":"1713959478572"},{"key":"iter_4_calc_sums","value":"1713959480198"},{"key":"iter_4_reduce","value":"1713959481008"},{"key":"iter_4_calc_err","value":"1713959481008"},{"key":"iter_4_broadcast_err","value":"1713959489276"},{"key":"iter_4_end","value":"1713959489439"},{"key":"iter_5_start","value":"1713959489439"},{"key":"iter_5_broadcast_weights","value":"1713959495466"},{"key":"iter_5_calc_sums","value":"1713959497022"},{"key":"iter_5_reduce","value":"1713959497890"},{"key":"iter_5_calc_err","value":"1713959497890"},{"key":"iter_5_broadcast_err","value":"1713959506340"},{"key":"iter_5_end","value":"1713959506507"},{"key":"iter_6_start","value":"1713959506507"},{"key":"iter_6_broadcast_weights","value":"1713959512613"},{"key":"iter_6_calc_sums","value":"1713959514103"},{"key":"iter_6_reduce","value":"1713959514917"},{"key":"iter_6_calc_err","value":"1713959514917"},{"key":"iter_6_broadcast_err","value":"1713959523444"},{"key":"iter_6_end","value":"1713959523617"},{"key":"iter_7_start","value":"1713959523617"},{"key":"iter_7_broadcast_weights","value":"1713959529667"},{"key":"iter_7_calc_sums","value":"1713959531225"},{"key":"iter_7_reduce","value":"1713959532004"},{"key":"iter_7_calc_err","value":"1713959532004"},{"key":"iter_7_broadcast_err","value":"1713959540621"},{"key":"iter_7_end","value":"1713959540794"},{"key":"iter_8_start","value":"1713959540794"},{"key":"iter_8_broadcast_weights","value":"1713959546934"},{"key":"iter_8_calc_sums","value":"1713959548485"},{"key":"iter_8_reduce","value":"1713959549278"},{"key":"iter_8_calc_err","value":"1713959549278"},{"key":"iter_8_broadcast_err","value":"1713959557888"},{"key":"iter_8_end","value":"1713959558057"},{"key":"iter_9_start","value":"1713959558057"},{"key":"iter_9_broadcast_weights","value":"1713959564809"},{"key":"iter_9_calc_sums","value":"1713959566617"},{"key":"iter_9_reduce","value":"1713959567487"},{"key":"iter_9_calc_err","value":"1713959567487"},{"key":"iter_9_broadcast_err","value":"1713959574902"},{"key":"iter_9_end","value":"1713959575078"},{"key":"worker_end","value":"1713959575078"}]}]