[{"bucket":"pagerank-burst","key":"bigdata/edges/part-00216","timestamps":[{"key":"worker_start","value":"1713959400365"},{"key":"get_input","value":"1713959403861"},{"key":"calc_outlinks","value":"1713959403902"},{"key":"iter_0_start","value":"1713959403902"},{"key":"iter_0_broadcast_weights","value":"1713959409127"},{"key":"iter_0_calc_sums","value":"1713959411588"},{"key":"iter_0_reduce","value":"1713959417265"},{"key":"iter_0_calc_err","value":"1713959417265"},{"key":"iter_0_broadcast_err","value":"1713959421311"},{"key":"iter_0_end","value":"1713959421463"},{"key":"iter_1_start","value":"1713959421463"},{"key":"iter_1_broadcast_weights","value":"1713959427410"},{"key":"iter_1_calc_sums","value":"1713959428691"},{"key":"iter_1_reduce","value":"1713959434320"},{"key":"iter_1_calc_err","value":"1713959434320"},{"key":"iter_1_broadcast_err","value":"1713959438223"},{"key":"iter_1_end","value":"1713959438361"},{"key":"iter_2_start","value":"1713959438361"},{"key":"iter_2_broadcast_weights","value":"1713959444157"},{"key":"iter_2_calc_sums","value":"1713959445418"},{"key":"iter_2_reduce","value":"1713959451139"},{"key":"iter_2_calc_err","value":"1713959451139"},{"key":"iter_2_broadcast_err","value":"1713959455193"},{"key":"iter_2_end","value":"1713959455344"},{"key":"iter_3_start","value":"1713959455344"},{"key":"iter_3_broadcast_weights","value":"1713959461314"},{"key":"iter_3_calc_sums","value":"1713959462551"},{"key":"iter_3_reduce","value":"1713959467665"},{"key":"iter_3_calc_err","value":"1713959467665"},{"key":"iter_3_broadcast_err","value":"1713959472077"},{"key":"iter_3_end","value":"1713959472228"},{"key":"iter_4_start","value":"1713959472228"},{"key":"iter_4_broadcast_weights","value":"1713959478554"},{"key":"iter_4_calc_sums","value":"1713959479934"},{"key":"iter_4_reduce","value":"1713959485438"},{"key":"iter_4_calc_err","value":"1713959485438"},{"key":"iter_4_broadcast_err","value":"1713959489272"},{"key":"iter_4_end","value":"1713959489419"},{"key":"iter_5_start","value":"1713959489419"},{"key":"iter_5_broadcast_weights","value":"1713959495302"},{"key":"iter_5_calc_sums","value":"1713959496609"},{"key":"iter_5_reduce","value":"1713959502088"},{"key":"iter_5_calc_err","value":"1713959502088"},{"key":"iter_5_broadcast_err","value":"1713959506335"},{"key":"iter_5_end","value":"1713959506473"},{"key":"iter_6_start","value":"1713959506473"},{"key":"iter_6_broadcast_weights","value":"1713959512315"},{"key":"iter_6_calc_sums","value":"1713959513460"},{"key":"iter_6_reduce","value":"1713959519248"},{"key":"iter_6_calc_err","value":"1713959519248"},{"key":"iter_6_broadcast_err","value":"1713959523439"},{"key":"iter_6_end","value":"1713959523592"},{"key":"iter_7_start","value":"1713959523592"},{"key":"iter_7_broadcast_weights","value":"1713959529517"},{"key":"iter_7_calc_sums","value":"1713959530824"},{"key":"iter_7_reduce","value":"1713959535888"},{"key":"iter_7_calc_err","value":"1713959535888"},{"key":"iter_7_broadcast_err","value":"1713959540617"},{"key":"iter_7_end","value":"1713959540763"},{"key":"iter_8_start","value":"1713959540763"},{"key":"iter_8_broadcast_weights","value":"1713959546858"},{"key":"iter_8_calc_sums","value":"1713959548129"},{"key":"iter_8_reduce","value":"1713959553735"},{"key":"iter_8_calc_err","value":"1713959553735"},{"key":"iter_8_broadcast_err","value":"1713959557884"},{"key":"iter_8_end","value":"1713959558019"},{"key":"iter_9_start","value":"1713959558019"},{"key":"iter_9_broadcast_weights","value":"1713959564022"},{"key":"iter_9_calc_sums","value":"1713959565298"},{"key":"iter_9_reduce","value":"1713959570641"},{"key":"iter_9_calc_err","value":"1713959570641"},{"key":"iter_9_broadcast_err","value":"1713959574897"},{"key":"iter_9_end","value":"1713959575040"},{"key":"worker_end","value":"1713959575040"}]},{"bucket":"pagerank-burst","key":"bigdata/edges/part-00217","timestamps":[{"key":"worker_start","value":"1713959400365"},{"key":"get_input","value":"1713959403589"},{"key":"calc_outlinks","value":"1713959403614"},{"key":"iter_0_start","value":"1713959403614"},{"key":"iter_0_broadcast_weights","value":"1713959409662"},{"key":"iter_0_calc_sums","value":"1713959411823"},{"key":"iter_0_reduce","value":"1713959412745"},{"key":"iter_0_calc_err","value":"1713959412745"},{"key":"iter_0_broadcast_err","value":"1713959421311"},{"key":"iter_0_end","value":"1713959421469"},{"key":"iter_1_start","value":"1713959421469"},{"key":"iter_1_broadcast_weights","value":"1713959427294"},{"key":"iter_1_calc_sums","value":"1713959428619"},{"key":"iter_1_reduce","value":"1713959429347"},{"key":"iter_1_calc_err","value":"1713959429347"},{"key":"iter_1_broadcast_err","value":"1713959438224"},{"key":"iter_1_end","value":"1713959438375"},{"key":"iter_2_start","value":"1713959438375"},{"key":"iter_2_broadcast_weights","value":"1713959444414"},{"key":"iter_2_calc_sums","value":"1713959445741"},{"key":"iter_2_reduce","value":"1713959446426"},{"key":"iter_2_calc_err","value":"1713959446426"},{"key":"iter_2_broadcast_err","value":"1713959455193"},{"key":"iter_2_end","value":"1713959455343"},{"key":"iter_3_start","value":"1713959455343"},{"key":"iter_3_broadcast_weights","value":"1713959461359"},{"key":"iter_3_calc_sums","value":"1713959462692"},{"key":"iter_3_reduce","value":"1713959463445"},{"key":"iter_3_calc_err","value":"1713959463445"},{"key":"iter_3_broadcast_err","value":"1713959472077"},{"key":"iter_3_end","value":"1713959472224"},{"key":"iter_4_start","value":"1713959472224"},{"key":"iter_4_broadcast_weights","value":"1713959478604"},{"key":"iter_4_calc_sums","value":"1713959479979"},{"key":"iter_4_reduce","value":"1713959480921"},{"key":"iter_4_calc_err","value":"1713959480921"},{"key":"iter_4_broadcast_err","value":"1713959489272"},{"key":"iter_4_end","value":"1713959489424"},{"key":"iter_5_start","value":"1713959489424"},{"key":"iter_5_broadcast_weights","value":"1713959495212"},{"key":"iter_5_calc_sums","value":"1713959496515"},{"key":"iter_5_reduce","value":"1713959497228"},{"key":"iter_5_calc_err","value":"1713959497228"},{"key":"iter_5_broadcast_err","value":"1713959506335"},{"key":"iter_5_end","value":"1713959506486"},{"key":"iter_6_start","value":"1713959506486"},{"key":"iter_6_broadcast_weights","value":"1713959512437"},{"key":"iter_6_calc_sums","value":"1713959513616"},{"key":"iter_6_reduce","value":"1713959514298"},{"key":"iter_6_calc_err","value":"1713959514298"},{"key":"iter_6_broadcast_err","value":"1713959523439"},{"key":"iter_6_end","value":"1713959523573"},{"key":"iter_7_start","value":"1713959523573"},{"key":"iter_7_broadcast_weights","value":"1713959530076"},{"key":"iter_7_calc_sums","value":"1713959531306"},{"key":"iter_7_reduce","value":"1713959532015"},{"key":"iter_7_calc_err","value":"1713959532015"},{"key":"iter_7_broadcast_err","value":"1713959540617"},{"key":"iter_7_end","value":"1713959540748"},{"key":"iter_8_start","value":"1713959540748"},{"key":"iter_8_broadcast_weights","value":"1713959547324"},{"key":"iter_8_calc_sums","value":"1713959548588"},{"key":"iter_8_reduce","value":"1713959549395"},{"key":"iter_8_calc_err","value":"1713959549395"},{"key":"iter_8_broadcast_err","value":"1713959557884"},{"key":"iter_8_end","value":"1713959558032"},{"key":"iter_9_start","value":"1713959558032"},{"key":"iter_9_broadcast_weights","value":"1713959564099"},{"key":"iter_9_calc_sums","value":"1713959565347"},{"key":"iter_9_reduce","value":"1713959566141"},{"key":"iter_9_calc_err","value":"1713959566141"},{"key":"iter_9_broadcast_err","value":"1713959574897"},{"key":"iter_9_end","value":"1713959575047"},{"key":"worker_end","value":"1713959575047"}]},{"bucket":"pagerank-burst","key":"bigdata/edges/part-00218","timestamps":[{"key":"worker_start","value":"1713959400365"},{"key":"get_input","value":"1713959403905"},{"key":"calc_outlinks","value":"1713959403934"},{"key":"iter_0_start","value":"1713959403934"},{"key":"iter_0_broadcast_weights","value":"1713959409022"},{"key":"iter_0_calc_sums","value":"1713959411573"},{"key":"iter_0_reduce","value":"1713959413859"},{"key":"iter_0_calc_err","value":"1713959413859"},{"key":"iter_0_broadcast_err","value":"1713959421311"},{"key":"iter_0_end","value":"1713959421464"},{"key":"iter_1_start","value":"1713959421464"},{"key":"iter_1_broadcast_weights","value":"1713959427810"},{"key":"iter_1_calc_sums","value":"1713959429157"},{"key":"iter_1_reduce","value":"1713959430617"},{"key":"iter_1_calc_err","value":"1713959430617"},{"key":"iter_1_broadcast_err","value":"1713959438224"},{"key":"iter_1_end","value":"1713959438373"},{"key":"iter_2_start","value":"1713959438373"},{"key":"iter_2_broadcast_weights","value":"1713959444360"},{"key":"iter_2_calc_sums","value":"1713959445656"},{"key":"iter_2_reduce","value":"1713959447890"},{"key":"iter_2_calc_err","value":"1713959447890"},{"key":"iter_2_broadcast_err","value":"1713959455193"},{"key":"iter_2_end","value":"1713959455340"},{"key":"iter_3_start","value":"1713959455340"},{"key":"iter_3_broadcast_weights","value":"1713959461726"},{"key":"iter_3_calc_sums","value":"1713959462888"},{"key":"iter_3_reduce","value":"1713959464540"},{"key":"iter_3_calc_err","value":"1713959464540"},{"key":"iter_3_broadcast_err","value":"1713959472077"},{"key":"iter_3_end","value":"1713959472223"},{"key":"iter_4_start","value":"1713959472223"},{"key":"iter_4_broadcast_weights","value":"1713959478997"},{"key":"iter_4_calc_sums","value":"1713959480398"},{"key":"iter_4_reduce","value":"1713959481872"},{"key":"iter_4_calc_err","value":"1713959481872"},{"key":"iter_4_broadcast_err","value":"1713959489272"},{"key":"iter_4_end","value":"1713959489417"},{"key":"iter_5_start","value":"1713959489417"},{"key":"iter_5_broadcast_weights","value":"1713959495804"},{"key":"iter_5_calc_sums","value":"1713959497206"},{"key":"iter_5_reduce","value":"1713959498705"},{"key":"iter_5_calc_err","value":"1713959498705"},{"key":"iter_5_broadcast_err","value":"1713959506335"},{"key":"iter_5_end","value":"1713959506470"},{"key":"iter_6_start","value":"1713959506470"},{"key":"iter_6_broadcast_weights","value":"1713959512951"},{"key":"iter_6_calc_sums","value":"1713959514306"},{"key":"iter_6_reduce","value":"1713959515740"},{"key":"iter_6_calc_err","value":"1713959515740"},{"key":"iter_6_broadcast_err","value":"1713959523439"},{"key":"iter_6_end","value":"1713959523589"},{"key":"iter_7_start","value":"1713959523589"},{"key":"iter_7_broadcast_weights","value":"1713959529436"},{"key":"iter_7_calc_sums","value":"1713959530756"},{"key":"iter_7_reduce","value":"1713959532571"},{"key":"iter_7_calc_err","value":"1713959532571"},{"key":"iter_7_broadcast_err","value":"1713959540617"},{"key":"iter_7_end","value":"1713959540762"},{"key":"iter_8_start","value":"1713959540762"},{"key":"iter_8_broadcast_weights","value":"1713959546885"},{"key":"iter_8_calc_sums","value":"1713959548159"},{"key":"iter_8_reduce","value":"1713959549949"},{"key":"iter_8_calc_err","value":"1713959549949"},{"key":"iter_8_broadcast_err","value":"1713959557884"},{"key":"iter_8_end","value":"1713959558021"},{"key":"iter_9_start","value":"1713959558021"},{"key":"iter_9_broadcast_weights","value":"1713959564543"},{"key":"iter_9_calc_sums","value":"1713959565737"},{"key":"iter_9_reduce","value":"1713959567381"},{"key":"iter_9_calc_err","value":"1713959567381"},{"key":"iter_9_broadcast_err","value":"1713959574897"},{"key":"iter_9_end","value":"1713959575034"},{"key":"worker_end","value":"1713959575034"}]},{"bucket":"pagerank-burst","key":"bigdata/edges/part-00219","timestamps":[{"key":"worker_start","value":"1713959400366"},{"key":"get_input","value":"1713959403652"},{"key":"calc_outlinks","value":"1713959403680"},{"key":"iter_0_start","value":"1713959403680"},{"key":"iter_0_broadcast_weights","value":"1713959408788"},{"key":"iter_0_calc_sums","value":"1713959411515"},{"key":"iter_0_reduce","value":"1713959412503"},{"key":"iter_0_calc_err","value":"1713959412503"},{"key":"iter_0_broadcast_err","value":"1713959421311"},{"key":"iter_0_end","value":"1713959421469"},{"key":"iter_1_start","value":"1713959421469"},{"key":"iter_1_broadcast_weights","value":"1713959427342"},{"key":"iter_1_calc_sums","value":"1713959428683"},{"key":"iter_1_reduce","value":"1713959429416"},{"key":"iter_1_calc_err","value":"1713959429416"},{"key":"iter_1_broadcast_err","value":"1713959438224"},{"key":"iter_1_end","value":"1713959438372"},{"key":"iter_2_start","value":"1713959438372"},{"key":"iter_2_broadcast_weights","value":"1713959444711"},{"key":"iter_2_calc_sums","value":"1713959446123"},{"key":"iter_2_reduce","value":"1713959446801"},{"key":"iter_2_calc_err","value":"1713959446801"},{"key":"iter_2_broadcast_err","value":"1713959455193"},{"key":"iter_2_end","value":"1713959455341"},{"key":"iter_3_start","value":"1713959455341"},{"key":"iter_3_broadcast_weights","value":"1713959461217"},{"key":"iter_3_calc_sums","value":"1713959462528"},{"key":"iter_3_reduce","value":"1713959463245"},{"key":"iter_3_calc_err","value":"1713959463245"},{"key":"iter_3_broadcast_err","value":"1713959472077"},{"key":"iter_3_end","value":"1713959472229"},{"key":"iter_4_start","value":"1713959472229"},{"key":"iter_4_broadcast_weights","value":"1713959478586"},{"key":"iter_4_calc_sums","value":"1713959479979"},{"key":"iter_4_reduce","value":"1713959480813"},{"key":"iter_4_calc_err","value":"1713959480813"},{"key":"iter_4_broadcast_err","value":"1713959489272"},{"key":"iter_4_end","value":"1713959489419"},{"key":"iter_5_start","value":"1713959489419"},{"key":"iter_5_broadcast_weights","value":"1713959495367"},{"key":"iter_5_calc_sums","value":"1713959496760"},{"key":"iter_5_reduce","value":"1713959497473"},{"key":"iter_5_calc_err","value":"1713959497473"},{"key":"iter_5_broadcast_err","value":"1713959506335"},{"key":"iter_5_end","value":"1713959506480"},{"key":"iter_6_start","value":"1713959506480"},{"key":"iter_6_broadcast_weights","value":"1713959512269"},{"key":"iter_6_calc_sums","value":"1713959513455"},{"key":"iter_6_reduce","value":"1713959514081"},{"key":"iter_6_calc_err","value":"1713959514081"},{"key":"iter_6_broadcast_err","value":"1713959523439"},{"key":"iter_6_end","value":"1713959523591"},{"key":"iter_7_start","value":"1713959523591"},{"key":"iter_7_broadcast_weights","value":"1713959529343"},{"key":"iter_7_calc_sums","value":"1713959530573"},{"key":"iter_7_reduce","value":"1713959531282"},{"key":"iter_7_calc_err","value":"1713959531282"},{"key":"iter_7_broadcast_err","value":"1713959540617"},{"key":"iter_7_end","value":"1713959540760"},{"key":"iter_8_start","value":"1713959540760"},{"key":"iter_8_broadcast_weights","value":"1713959546753"},{"key":"iter_8_calc_sums","value":"1713959548118"},{"key":"iter_8_reduce","value":"1713959548852"},{"key":"iter_8_calc_err","value":"1713959548852"},{"key":"iter_8_broadcast_err","value":"1713959557884"},{"key":"iter_8_end","value":"1713959558034"},{"key":"iter_9_start","value":"1713959558034"},{"key":"iter_9_broadcast_weights","value":"1713959564152"},{"key":"iter_9_calc_sums","value":"1713959565482"},{"key":"iter_9_reduce","value":"1713959566314"},{"key":"iter_9_calc_err","value":"1713959566314"},{"key":"iter_9_broadcast_err","value":"1713959574897"},{"key":"iter_9_end","value":"1713959575043"},{"key":"worker_end","value":"1713959575044"}]}]