[{"bucket":"pagerank-burst","key":"bigdata/edges/part-00039","timestamps":[{"key":"worker_start","value":"1713956798018"},{"key":"get_input","value":"1713956801188"},{"key":"calc_outlinks","value":"1713956801236"},{"key":"iter_0_start","value":"1713956801236"},{"key":"iter_0_broadcast_weights","value":"1713956867520"},{"key":"iter_0_calc_sums","value":"1713956869525"},{"key":"iter_0_reduce","value":"1713956877282"},{"key":"iter_0_calc_err","value":"1713956877282"},{"key":"iter_0_broadcast_err","value":"1713956893256"},{"key":"iter_0_end","value":"1713956893317"},{"key":"iter_1_start","value":"1713956893317"},{"key":"iter_1_broadcast_weights","value":"1713956958830"},{"key":"iter_1_calc_sums","value":"1713956960554"},{"key":"iter_1_reduce","value":"1713956968017"},{"key":"iter_1_calc_err","value":"1713956968017"},{"key":"iter_1_broadcast_err","value":"1713956984458"},{"key":"iter_1_end","value":"1713956984519"},{"key":"iter_2_start","value":"1713956984519"},{"key":"iter_2_broadcast_weights","value":"1713957050560"},{"key":"iter_2_calc_sums","value":"1713957051810"},{"key":"iter_2_reduce","value":"1713957060606"},{"key":"iter_2_calc_err","value":"1713957060606"},{"key":"iter_2_broadcast_err","value":"1713957076622"},{"key":"iter_2_end","value":"1713957076682"},{"key":"iter_3_start","value":"1713957076682"},{"key":"iter_3_broadcast_weights","value":"1713957142058"},{"key":"iter_3_calc_sums","value":"1713957143353"},{"key":"iter_3_reduce","value":"1713957151403"},{"key":"iter_3_calc_err","value":"1713957151403"},{"key":"iter_3_broadcast_err","value":"1713957167825"},{"key":"iter_3_end","value":"1713957167886"},{"key":"iter_4_start","value":"1713957167886"},{"key":"iter_4_broadcast_weights","value":"1713957235209"},{"key":"iter_4_calc_sums","value":"1713957236430"},{"key":"iter_4_reduce","value":"1713957245370"},{"key":"iter_4_calc_err","value":"1713957245370"},{"key":"iter_4_broadcast_err","value":"1713957261714"},{"key":"iter_4_end","value":"1713957261774"},{"key":"iter_5_start","value":"1713957261774"},{"key":"iter_5_broadcast_weights","value":"1713957328775"},{"key":"iter_5_calc_sums","value":"1713957329894"},{"key":"iter_5_reduce","value":"1713957338407"},{"key":"iter_5_calc_err","value":"1713957338407"},{"key":"iter_5_broadcast_err","value":"1713957355099"},{"key":"iter_5_end","value":"1713957355195"},{"key":"iter_6_start","value":"1713957355195"},{"key":"iter_6_broadcast_weights","value":"1713957423923"},{"key":"iter_6_calc_sums","value":"1713957425193"},{"key":"iter_6_reduce","value":"1713957433052"},{"key":"iter_6_calc_err","value":"1713957433052"},{"key":"iter_6_broadcast_err","value":"1713957450201"},{"key":"iter_6_end","value":"1713957450262"},{"key":"iter_7_start","value":"1713957450262"},{"key":"iter_7_broadcast_weights","value":"1713957517490"},{"key":"iter_7_calc_sums","value":"1713957518690"},{"key":"iter_7_reduce","value":"1713957527738"},{"key":"iter_7_calc_err","value":"1713957527738"},{"key":"iter_7_broadcast_err","value":"1713957543351"},{"key":"iter_7_end","value":"1713957543412"},{"key":"iter_8_start","value":"1713957543412"},{"key":"iter_8_broadcast_weights","value":"1713957611766"},{"key":"iter_8_calc_sums","value":"1713957613151"},{"key":"iter_8_reduce","value":"1713957621827"},{"key":"iter_8_calc_err","value":"1713957621827"},{"key":"iter_8_broadcast_err","value":"1713957638189"},{"key":"iter_8_end","value":"1713957638256"},{"key":"iter_9_start","value":"1713957638256"},{"key":"iter_9_broadcast_weights","value":"1713957706249"},{"key":"iter_9_calc_sums","value":"1713957707516"},{"key":"iter_9_reduce","value":"1713957716191"},{"key":"iter_9_calc_err","value":"1713957716191"},{"key":"iter_9_broadcast_err","value":"1713957732597"},{"key":"iter_9_end","value":"1713957732659"},{"key":"worker_end","value":"1713957732659"}]}]