[{"bucket":"pagerank-burst","key":"bigdata/edges/part-00068","timestamps":[{"key":"worker_start","value":"1713956798287"},{"key":"get_input","value":"1713956802677"},{"key":"calc_outlinks","value":"1713956802702"},{"key":"iter_0_start","value":"1713956802703"},{"key":"iter_0_broadcast_weights","value":"1713956866939"},{"key":"iter_0_calc_sums","value":"1713956868858"},{"key":"iter_0_reduce","value":"1713956883947"},{"key":"iter_0_calc_err","value":"1713956883947"},{"key":"iter_0_broadcast_err","value":"1713956893329"},{"key":"iter_0_end","value":"1713956893437"},{"key":"iter_1_start","value":"1713956893437"},{"key":"iter_1_broadcast_weights","value":"1713956958535"},{"key":"iter_1_calc_sums","value":"1713956959949"},{"key":"iter_1_reduce","value":"1713956975101"},{"key":"iter_1_calc_err","value":"1713956975101"},{"key":"iter_1_broadcast_err","value":"1713956984535"},{"key":"iter_1_end","value":"1713956984646"},{"key":"iter_2_start","value":"1713956984646"},{"key":"iter_2_broadcast_weights","value":"1713957050922"},{"key":"iter_2_calc_sums","value":"1713957052342"},{"key":"iter_2_reduce","value":"1713957067917"},{"key":"iter_2_calc_err","value":"1713957067917"},{"key":"iter_2_broadcast_err","value":"1713957076697"},{"key":"iter_2_end","value":"1713957076807"},{"key":"iter_3_start","value":"1713957076807"},{"key":"iter_3_broadcast_weights","value":"1713957142338"},{"key":"iter_3_calc_sums","value":"1713957143786"},{"key":"iter_3_reduce","value":"1713957158555"},{"key":"iter_3_calc_err","value":"1713957158555"},{"key":"iter_3_broadcast_err","value":"1713957167901"},{"key":"iter_3_end","value":"1713957167963"},{"key":"iter_4_start","value":"1713957167963"},{"key":"iter_4_broadcast_weights","value":"1713957235367"},{"key":"iter_4_calc_sums","value":"1713957236705"},{"key":"iter_4_reduce","value":"1713957252489"},{"key":"iter_4_calc_err","value":"1713957252489"},{"key":"iter_4_broadcast_err","value":"1713957261782"},{"key":"iter_4_end","value":"1713957261898"},{"key":"iter_5_start","value":"1713957261898"},{"key":"iter_5_broadcast_weights","value":"1713957329166"},{"key":"iter_5_calc_sums","value":"1713957330574"},{"key":"iter_5_reduce","value":"1713957346836"},{"key":"iter_5_calc_err","value":"1713957346836"},{"key":"iter_5_broadcast_err","value":"1713957355195"},{"key":"iter_5_end","value":"1713957355260"},{"key":"iter_6_start","value":"1713957355260"},{"key":"iter_6_broadcast_weights","value":"1713957423996"},{"key":"iter_6_calc_sums","value":"1713957425360"},{"key":"iter_6_reduce","value":"1713957441496"},{"key":"iter_6_calc_err","value":"1713957441496"},{"key":"iter_6_broadcast_err","value":"1713957450277"},{"key":"iter_6_end","value":"1713957450346"},{"key":"iter_7_start","value":"1713957450346"},{"key":"iter_7_broadcast_weights","value":"1713957517629"},{"key":"iter_7_calc_sums","value":"1713957518958"},{"key":"iter_7_reduce","value":"1713957534738"},{"key":"iter_7_calc_err","value":"1713957534738"},{"key":"iter_7_broadcast_err","value":"1713957543424"},{"key":"iter_7_end","value":"1713957543512"},{"key":"iter_8_start","value":"1713957543512"},{"key":"iter_8_broadcast_weights","value":"1713957611939"},{"key":"iter_8_calc_sums","value":"1713957613131"},{"key":"iter_8_reduce","value":"1713957629491"},{"key":"iter_8_calc_err","value":"1713957629491"},{"key":"iter_8_broadcast_err","value":"1713957638253"},{"key":"iter_8_end","value":"1713957638329"},{"key":"iter_9_start","value":"1713957638329"},{"key":"iter_9_broadcast_weights","value":"1713957706830"},{"key":"iter_9_calc_sums","value":"1713957708341"},{"key":"iter_9_reduce","value":"1713957723554"},{"key":"iter_9_calc_err","value":"1713957723554"},{"key":"iter_9_broadcast_err","value":"1713957732665"},{"key":"iter_9_end","value":"1713957732753"},{"key":"worker_end","value":"1713957732753"}]}]